annotator/__init__.py
annotator/admin.py
annotator/apps.py
annotator/filters.py
annotator/migrations/0001_initial.py
annotator/migrations/__init__.py
annotator/models.py
annotator/serializers.py
annotator/static/js/annotator.min.js
annotator/templates/annotator/demo.html
annotator/tests/__init__.py
annotator/tests/test_views.py
annotator/urls.py
annotator/views.py
django_annotator-2.2.11.dist-info/METADATA
django_annotator-2.2.11.dist-info/WHEEL
django_annotator-2.2.11.dist-info/licenses/LICENSE
django_annotator-2.2.11.dist-info/RECORD
