Metadata-Version: 2.4
Name: django-annotator
Version: 2.2.11
Summary: Implementation of annotatorjs's Storage/Search API.
License: Apache-2.0
License-File: LICENSE
Author: PsypherPunk
Author-email: psypherpunk@gmail.com
Requires-Python: >=3.10,<4.0
Classifier: License :: OSI Approved :: Apache Software License
Classifier: Programming Language :: Python :: 3
Classifier: Programming Language :: Python :: 3.10
Classifier: Programming Language :: Python :: 3.11
Classifier: Programming Language :: Python :: 3.12
Classifier: Programming Language :: Python :: 3.13
Classifier: Programming Language :: Python :: 3.14
Requires-Dist: django-filter (>=24.2,<25.0)
Requires-Dist: djangorestframework (>=3.15.2,<4.0.0)
Requires-Dist: drf-writable-nested (>=0.7.0,<0.8.0)
